sydney_magic/__init__.py
sydney_magic/sydney_magic-Copy1.py
sydney_magic/sydney_magic.py
sydney_magic-0.27.dist-info/METADATA
sydney_magic-0.27.dist-info/WHEEL
sydney_magic-0.27.dist-info/top_level.txt
sydney_magic-0.27.dist-info/RECORD
