Metadata-Version: 2.1
Name: sydney_magic
Version: 0.27
Summary: An IPython magic extension for interacting with Sydney.py
Home-page: https://github.com/KPEKEP/sydney-magic/
Download-URL: https://github.com/KPEKEP/sydney-magic/sydney_magic-0.27tar.gz
Author: Pavel Nakaznenko
Author-email: p.nakaznenko@gmail.com
Keywords: ipython magic sydney
Requires-Dist: IPython
Requires-Dist: sydney-py
Requires-Dist: nest-asyncio
Requires-Dist: ipynbname
